asdicts/__init__.py
asdicts/dict.py
asdicts-1.1.0.dist-info/LICENSE
asdicts-1.1.0.dist-info/METADATA
asdicts-1.1.0.dist-info/WHEEL
asdicts-1.1.0.dist-info/top_level.txt
asdicts-1.1.0.dist-info/RECORD
