Metadata-Version: 2.1
Name: asdicts
Version: 1.1.0
Summary: Missed utilities for working with Python dictionaries
Home-page: https://github.com/sergeyklay/asdicts
Author: Serghei Iakovlev
Author-email: egrep@protonmail.ch
Maintainer: Serghei Iakovlev
Maintainer-email: egrep@protonmail.ch
License: Apache 2.0
Project-URL: Bug Tracker, https://github.com/sergeyklay/asdicts/issues
Project-URL: Source Code, https://github.com/sergeyklay/asdicts
Keywords: dict,collections,helpers
Platform: any
Classifier: Development Status :: 5 - Production/Stable
Classifier: Intended Audience :: Developers
Classifier: Natural Language :: English
Classifier: License :: OSI Approved :: Apache Software License
Classifier: Operating System :: OS Independent
Classifier: Programming Language :: Python
Classifier: Programming Language :: Python :: 3
Classifier: Programming Language :: Python :: 3.6
Classifier: Programming Language :: Python :: 3.7
Classifier: Programming Language :: Python :: 3.8
Classifier: Programming Language :: Python :: 3.9
Classifier: Programming Language :: Python :: 3.10
Classifier: Programming Language :: Python :: 3 :: Only
Classifier: Topic :: Utilities
Requires-Python: >=3.6, <4
Provides-Extra: testing
Requires-Dist: pytest ; extra == 'testing'
